flask_bson.py
Flask_BSON-0.1.1.dist-info/DESCRIPTION.rst
Flask_BSON-0.1.1.dist-info/METADATA
Flask_BSON-0.1.1.dist-info/RECORD
Flask_BSON-0.1.1.dist-info/WHEEL
Flask_BSON-0.1.1.dist-info/metadata.json
Flask_BSON-0.1.1.dist-info/top_level.txt
